sier2_blocks_geo/blocks/__init__.py
sier2_blocks_geo/blocks/geo.py
sier2_blocks_geo/dags/__init__.py
sier2_blocks_geo/dags/geo_dags.py
sier2_blocks_geo/shelf/__init__.py
sier2_blocks_geo-0.6.dist-info/LICENSE
sier2_blocks_geo-0.6.dist-info/METADATA
sier2_blocks_geo-0.6.dist-info/WHEEL
sier2_blocks_geo-0.6.dist-info/entry_points.txt
sier2_blocks_geo-0.6.dist-info/RECORD
